django_rest_admin/__init__.py
django_rest_admin/admin.py
django_rest_admin/apps.py
django_rest_admin/get_app_url_base.py
django_rest_admin/get_table_foreignkey_param.py
django_rest_admin/json_widget.py
django_rest_admin/model_field.py
django_rest_admin/models.py
django_rest_admin/my_rest_api.py
django_rest_admin/set_table_default_value.py
django_rest_admin/tests.py
django_rest_admin/update_models.py
django_rest_admin/update_rest.py
django_rest_admin/update_table_list.py
django_rest_admin/urls.py
django_rest_admin/urls_template.py
django_rest_admin/views.py
django_rest_admin/migrations/0001_initial.py
django_rest_admin/migrations/0002_alter_routeexec_options.py
django_rest_admin/migrations/0003_dbtabletorest.py
django_rest_admin/migrations/0004_dbtabletorest_model_name.py
django_rest_admin/migrations/0005_alter_dbtabletorest_options.py
django_rest_admin/migrations/0006_dbtabletorest_t_type.py
django_rest_admin/migrations/__init__.py
django_rest_admin/static/django_rest_admin/jquery-3.6.0.min.js
django_rest_admin/static/django_rest_admin/jsoneditor.css
django_rest_admin/static/django_rest_admin/jsoneditor.js
django_rest_admin/static/django_rest_admin/img/jsoneditor-icons.svg
django_rest_admin/templates/html/auto_refresh_list.html
django_rest_admin/templates/html/table_to_rest_list.html
django_rest_admin-0.1.9.dist-info/LICENSE
django_rest_admin-0.1.9.dist-info/METADATA
django_rest_admin-0.1.9.dist-info/WHEEL
django_rest_admin-0.1.9.dist-info/top_level.txt
django_rest_admin-0.1.9.dist-info/RECORD
