Metadata-Version: 2.1
Name: django-rest-admin
Version: 0.1.9
Summary: django app for Adding table CRUD rest api with admin ui and without coding.
Home-page: https://github.com/Jiangshan00001/django_rest_admin
Author: jiangshan00000
Author-email: 710806594@qq.com
License: UNKNOWN
Platform: UNKNOWN
Classifier: Programming Language :: Python :: 3
Classifier: License :: OSI Approved :: MIT License
Classifier: Operating System :: OS Independent
License-File: LICENSE
Requires-Dist: django
Requires-Dist: django-filter
Requires-Dist: djangorestframework
